py_library/__init__.py
py_library/kafka_conn.py
py_library/mysql_conn.py
py_library/redis_conn.py
py_library/async_db/__init__.py
py_library/async_db/env.py
py_library/async_db/mysql_db.py
py_library/async_db/postgresql_db.py
py_library/async_db/redis_db.py
py_library-1.0.15.dist-info/licenses/LICENSE
py_library-1.0.15.dist-info/METADATA
py_library-1.0.15.dist-info/WHEEL
py_library-1.0.15.dist-info/top_level.txt
py_library-1.0.15.dist-info/RECORD
