Metadata-Version: 2.4
Name: Py-library
Version: 1.0.15
Summary: py 工具箱
Home-page: https://github.com/CLannadZSY/Tools
Author: CLannadZSY
Author-email: zsymidi@gmail.com
Classifier: Programming Language :: Python :: 3
Classifier: License :: OSI Approved :: MIT License
Classifier: Operating System :: OS Independent
Requires-Python: >=3.6
License-File: LICENSE
Dynamic: author
Dynamic: author-email
Dynamic: classifier
Dynamic: description
Dynamic: description-content-type
Dynamic: home-page
Dynamic: license-file
Dynamic: requires-python
Dynamic: summary
